MANIFEST.in
setup.py
pysvc/__init__.py
pysvc/errors.py
pysvc/examples.py
pysvc/messages.py
pysvc.egg-info/PKG-INFO
pysvc.egg-info/SOURCES.txt
pysvc.egg-info/dependency_links.txt
pysvc.egg-info/requires.txt
pysvc.egg-info/top_level.txt
pysvc/transports/__init__.py
pysvc/transports/ssh_transport.py
pysvc/transports/transport.py
pysvc/unified/__init__.py
pysvc/unified/client.py
pysvc/unified/clispec.py
pysvc/unified/errors.py
pysvc/unified/response.py
pysvc/unified/scp_cli_client.py
pysvc/unified/xsf-1.0.xml
pysvc/unified/helpers/__init__.py
pysvc/unified/helpers/etree.py
pysvc/unified/helpers/exceptool.py
pysvc/unified/helpers/xml_util.py